gofiliate
