Metadata-Version: 1.1
Name: gofiliate
Version: 2.0.1
Summary: Gofiliate Python bindings.
Home-page: https://github.com/mgmonteleone/py-gofiliate-client
Author: iGP Technologies d.o.o.
Author-email: mgm@igpte.ch
License: BSD
Platform: UNKNOWN
Classifier: Environment :: Web Environment
Classifier: Intended Audience :: Developers
Classifier: License :: OSI Approved :: BSD License
Classifier: Operating System :: OS Independent
Classifier: Programming Language :: Python
Classifier: Programming Language :: Python :: 3.5
Classifier: Programming Language :: Python :: 3.6
